README
setup.py
jtlvi/__init__.py
jtlvi.egg-info/PKG-INFO
jtlvi.egg-info/SOURCES.txt
jtlvi.egg-info/dependency_links.txt
jtlvi.egg-info/top_level.txt
tests/__init__.py
tests/test_bsd_checksum.py
tests/test_jtlvi.py