Metadata-Version: 1.1
Name: jtlvi
Version: 1.0.1
Summary: JTLVI Message Format: Just TLV It!
Home-page: https://github.com/rfinnie/jtlvi
Author: Ryan Finnie
Author-email: ryan@finnie.org
License: BSD
Download-URL: https://github.com/rfinnie/jtlvi
Platform: Unix
Classifier: Development Status :: 5 - Production/Stable
Classifier: Intended Audience :: Developers
Classifier: License :: OSI Approved :: BSD License
Classifier: Programming Language :: Python :: 3 :: Only
Classifier: Programming Language :: Python :: Implementation :: PyPy
Classifier: Topic :: Software Development :: Libraries :: Python Modules
